odoo/addons/auth_jwt_demo/README.rst
odoo/addons/auth_jwt_demo/__init__.py
odoo/addons/auth_jwt_demo/__manifest__.py
odoo/addons/auth_jwt_demo/controllers/__init__.py
odoo/addons/auth_jwt_demo/controllers/main.py
odoo/addons/auth_jwt_demo/demo/auth_jwt_validator.xml
odoo/addons/auth_jwt_demo/i18n/auth_jwt_demo.pot
odoo/addons/auth_jwt_demo/i18n/it.po
odoo/addons/auth_jwt_demo/readme/CONTRIBUTORS.rst
odoo/addons/auth_jwt_demo/readme/DESCRIPTION.rst
odoo/addons/auth_jwt_demo/readme/USAGE.rst
odoo/addons/auth_jwt_demo/static/description/icon.png
odoo/addons/auth_jwt_demo/static/description/index.html
odoo/addons/auth_jwt_demo/tests/__init__.py
odoo/addons/auth_jwt_demo/tests/test_auth_jwt_demo.py
odoo/addons/auth_jwt_demo/tests/keycloak/keycloak-config.json
odoo/addons/auth_jwt_demo/tests/keycloak/keycloak.sh
odoo/addons/auth_jwt_demo/tests/spa/README.md
odoo/addons/auth_jwt_demo/tests/spa/auth_settings.json
odoo/addons/auth_jwt_demo/tests/spa/index.html
odoo/addons/auth_jwt_demo/tests/spa/js/app.js
odoo/addons/auth_jwt_demo/tests/spa/js/oidc-client.js
odoo_addon_auth_jwt_demo-16.0.1.1.1.1.dist-info/METADATA
odoo_addon_auth_jwt_demo-16.0.1.1.1.1.dist-info/WHEEL
odoo_addon_auth_jwt_demo-16.0.1.1.1.1.dist-info/top_level.txt
odoo_addon_auth_jwt_demo-16.0.1.1.1.1.dist-info/RECORD
