Metadata-Version: 2.1
Name: odoo-addon-auth-jwt-demo
Version: 16.0.1.1.1.1
Summary: Test/demo module for auth_jwt.
Home-page: https://github.com/OCA/server-auth
Author: ACSONE SA/NV,Odoo Community Association (OCA)
Author-email: support@odoo-community.org
License: LGPL-3
Platform: UNKNOWN
Classifier: Programming Language :: Python
Classifier: Framework :: Odoo
Classifier: Framework :: Odoo :: 16.0
Classifier: License :: OSI Approved :: GNU Lesser General Public License v3 (LGPLv3)
Requires-Python: >=3.10
Requires-Dist: odoo-addon-auth-jwt <16.1dev,>=16.0dev
Requires-Dist: odoo <16.1dev,>=16.0a
